grammar_school/__init__.py
grammar_school/ast.py
grammar_school/backend_lark.py
grammar_school/cfg_vendor.py
grammar_school/grammar.py
grammar_school/grammar_builder.py
grammar_school/grammar_config.py
grammar_school/interpreter.py
grammar_school/openai_utils.py
grammar_school/runtime.py
grammar_school/smart_transformer.py
grammar_school/version.py
grammar_school-0.6.0.dist-info/METADATA
grammar_school-0.6.0.dist-info/WHEEL
grammar_school-0.6.0.dist-info/top_level.txt
grammar_school-0.6.0.dist-info/RECORD
